{"4I1qEvlLTvDmHLD0Z9opaw==":"detourbus_keyart_laurels-1392x783.png","sphdbuR/N4BYkDoEDlcL3Q==":"triangles-1920x1280.png","/Xdb6O0YPvtG9i5bQS0wzA==":"jampakdd_1-1_white-96x96.png","VowlsCrEB9bCNkD/ozQ8kQ==":"beasts_keyartweb-1-741x417.png","asSq07u9ch28uf0Q0KKHDA==":"maxresdefault-924x520.jpg","dTHR431olU7n0H8n753RMA==":"demo-922x519.png","0WLEUUkZhENO2Zx8gBE2HQ==":"meowdy-purrtner-gameplay-2-435x244.png","468cvlfdKDXdtVtrosgJsQ==":"fireplace-924x519.jpg","09BMXFEt1Z5dOYDcggQUqA==":"paintakill3-746x420.png","117/MNLV8Gn/YsX47K8/Mg==":"vsb_pic-924x519.png","EmLrqjhwuU8M73WR/RYcwA==":"upbeatlogo-739x415.png","SBM7PQR8WwCOUYk77cRyUA==":"colorgrinderlogo-739x415.png","Nt3jgGpbnL9HlHqt/Rn+Gw==":"digdug-641x361.png","6x1GO2CGS+4tbitThZsj9w==":"the-gungan-tryst-343x192.png","/hsgG9rmiz8EH7zZkrOygA==":"moontower-634x357.png","p/IPYne71BSPvJ2/nmNkvg==":"img-1251-661x372.jpg","Accpc158RwNaEhDj+wmygA==":"img-4498-468x263.jpg","kLAqk3aspvV/usAcnaurLA==":"project%20princess-675x380.png","S1BWBDPLT2QPUf4YpkpGgg==":"hfwzcc-948x529.png","hjBy/JbsP5gQzr0nilb2XQ==":"zoomerbike-1-948x632.png","EsRKu4uEPakn9S1LLN6UwA==":"edited-696x1044.png","cyZdEanthJqkcMrpzf5Mgg==":"marshmallowdead-32x32.png","3e89vHD3E/ihbqvIALyyqQ==":"detourbus_poster_groovy_16x9-1-1646x926.png","1ea5OslNhCMnwjp7e5j75w==":"oculusannouncement-1076x1076.png","4o9WcaIwp58fsJB0XNtY5A==":"ejroroxxcaucw-z-696x696.jpg","lGK6tPM+K1hDsJHVxVCMrQ==":"steam-510x287.png","MzGLhLeyD8To/Bx1/WiFig==":"beastsweeklyburndownchart-1086x635.png","Ib0PtOHVt9M3FXVaaE2gUQ==":"standup-230x108.png","x0P7rqwahyKc5kpMWeDrKA==":"beautiful%20beach-4-890x499.png","dYnJvV2OBKjO3Ru0SIc4kg==":"beasts_highrez_keyart-1-2000x1247.png","ifpBxRtzL3hIH184N6I1BQ==":"beasts_highrez_keyart-2-2000x1247.png","IkrXPxxZ6xTBt3pT+OOQWw==":"waterfall%20concept%20art-2000x1337.png","QxFNoFIQQqfCNQK/s9G4kw==":"waterfall%20concept%20art-2000x1337.png","DMUOekRS5sIqFe+EL+gOww==":"beach_trawler-1-190x286.png","7DyNP7ukJdQOt08hKI6MTQ==":"journal%20concept%20art-1108x850.png","BwjSWfv4/UXDfPDkU1yD5w==":"spires1-1108x776.png","qnwJp4LIq0B9GXGTH6pRbw==":"leaves-1342x817.png","9wQ0PrhnCmPIgyp4WOmhXA==":"branches-1253x329.png","O36vNXgBmSlXBtYoOIuHdA==":"large%20walkable%20branches1-1153x964.png","NlCDvgzPDSxYLn7a0UZhqg==":"large%20walkable%20branches2-884x952.png","v1YYfTZAoJJdhwsUsjAiCA==":"large%20walkable%20branches3-2332x1251.png","GDO54NQhKNzGXWE1unXaAQ==":"spires-593x299.png","a0RO9MxtRWoXY20FIXhVAA==":"spires1-1553x1087.png","Tzq/vjY7I/+oHu6cc+t5pA==":"spires2-1942x1082.png","+fl4OSUzaUM15KyNBpjX/Q==":"marinaclimb.gif","bS+SVnhZ6WErF8QPImmskg==":"temple3-782x409.png","D+qSKaVXhnYXEIUH37zaEQ==":"temple2-874x783.png","vfN8ONph69bN3kfKFeJe2w==":"treeplanes2-507x401.png","m19Ix/NzknfhBd5Ei/IY6w==":"vines-1208x947.png","MoutoWoOgYxymBJtU6KlMQ==":"treeplanes1-1-1972x756.png","YH4xVNarri3wZ9r3R1zIKQ==":"treeplane5-1-552x789.png","SsaDA3IuYkyWeuRDqbJX3g==":"treeplane4-1-262x222.png","nKZhp2p2xNCVq/jUDEXKZw==":"treeplanes3-1-308x315.png","Gw85jwG6MB1Dt//MvFc4Dg==":"beautifulcorner-1126x631.png","tYtjPdk4kkdsKAGbR7a67w==":"beastslogoblack-1335x656.png","tkf0m6Nlut/6Msmz8h2k7w==":"beach_trawler-2552x1433.png","/wnyVyt33s+UnEEYMLt+cA==":"birbs-671x546.png","0P5i4HYWfHnoIhrwfBnYzA==":"trawler-2-2553x1434.png"}